{"title": "PERSON OF INTEREST S4 Preview Trailer", "url": "https://www.youtube.com/watch?v=2a55OLQOqF0", "image": "https://i.ytimg.com/vi/2a55OLQOqF0/hqdefault.jpg", "author": "CatchWitt", "viewCount": "9889", "datePublished": "2014-09-15", "likes": "71", "dislikes": "1", "comment": ["Friggen amazing! I just can't wait!", "what is the song"], "authorLink": "https://www.youtube.com/channel/UCbFvKliV5_ZksbnNm9AShFA", "description": "Samaritan is hunting Team Machine in S4. Finch, Reese, Fusco, Root and Shaw go undercover to save the numbers. Season 4 returns on September 23, 2014"}