{"title": "American Horror Story: Apocalypse 8x03 Promo - \"Forbidden Fruit\" (HD)", "url": "https://www.youtube.com/watch?v=3CtERSrHAIQ", "image": "https://i.ytimg.com/vi/3CtERSrHAIQ/maxresdefault.jpg", "author": "American Horror Story: Croatia", "viewCount": "412", "datePublished": "2018-09-20", "likes": "11", "dislikes": "0", "comment": [], "authorLink": "https://www.youtube.com/channel/UCbqN5wuVJi2x8RL3OFNjsUg", "description": "American Horror Story: Apocalypse 8x03 Promo - \"Forbidden Fruit\" (HD)\nAmeri\u010dka horor pri\u010da: Apokalipsa"}