{"title": "Person of Interest - Season 2 best fight scene", "url": "https://www.youtube.com/watch?v=4x6c74ufXfQ", "image": "https://i.ytimg.com/vi/4x6c74ufXfQ/maxresdefault.jpg", "author": "Novus Destiny", "viewCount": "6843", "datePublished": "2013-06-28", "likes": "26", "dislikes": "1", "comment": ["Government Assassin vs. Government Assassin."], "authorLink": "https://www.youtube.com/channel/UCm3IFcQ139HaWvvYksTaP4Q", "description": "Person of Interest - Season 2 Ep 15 Fight between Reese and Hersh"}