{"title": "John Reese || Monster || [Person of Interest]", "url": "https://www.youtube.com/watch?v=5Lu_W8rEEbA", "image": "https://i.ytimg.com/vi/5Lu_W8rEEbA/maxresdefault.jpg", "author": "KarxDanvers", "viewCount": "11804", "datePublished": "2015-07-07", "likes": "197", "dislikes": "1", "comment": ["Wow that's a great choice of song for Reese! Love this! :)", "so I have an rp char, and i use him as a char model and I semi based the char off of him and no matter how many videos i look at to use for him, this is the only video that fits him, this is amazing, it fits John Reese so much as well. It is a very well put together video. Well done", "Great video!! The song fits John so well! :D", "Make a Harry or Lirry video pls!! Or Narry or Zarry \ud83d\ude02", "\uc874 \ub9ac\uc2a4 I LOVE YOU!"], "authorLink": "https://www.youtube.com/channel/UCXYQu1yIgghYfeHbzH0t0ng", "description": ""}