{"title": "American Horror Story: Apocalypse 8x02 Promo - \"The Morning After\" (HD)", "url": "https://www.youtube.com/watch?v=6Q-gMjfvTKI", "image": "https://i.ytimg.com/vi/6Q-gMjfvTKI/maxresdefault.jpg", "author": "American Horror Story: Croatia", "viewCount": "383", "datePublished": "2018-09-15", "likes": "7", "dislikes": "0", "comment": [], "authorLink": "https://www.youtube.com/channel/UCbqN5wuVJi2x8RL3OFNjsUg", "description": "American Horror Story: Apocalypse 8x02 Promo - \"The Morning After\" (HD)\nAmeri\u010dka horor pri\u010da: Apokalipsa"}