{"title": "American Horror Story Weekly Wednesday Live Stream", "url": "https://www.youtube.com/watch?v=A-gFqWZg8cQ", "image": "https://i.ytimg.com/vi/A-gFqWZg8cQ/maxresdefault.jpg", "author": "MaryGirl Moody", "viewCount": "442", "datePublished": "2019-03-13", "likes": "38", "dislikes": "1", "comment": ["im hoping they show AHS :( its a big part of paleyfest but Ryan is already gonna be doing the pose and 9-1-1 panel", "If it\u2019s just a book did you say media mail? I just found out recently when I sent a book there is a cheaper rate.", "I love the new set up", "You are so dedicated talented and gorgeous you are everything Miss Queen Supreme", "Am so sorry Mary I did it come am so sorry I had school"], "authorLink": "https://www.youtube.com/channel/UCc5rwO1EcnOo6ydOmGItlGQ", "description": "Welcome to American Horror Story Weekly Wednesday Live Stream! Host is MaryGirl Moody. \n\n\u25ba \u25ba SUBSCRIBE https://www.youtube.com/channel/UCc5r..."}