{"title": "Teeth Sharpening | AHS: Double Feature - Episode 2: \"Pale\" (HQ Clip)", "url": "https://www.youtube.com/watch?v=Ak0wG7a9xpQ", "image": "https://i.ytimg.com/vi/Ak0wG7a9xpQ/hqdefault.jpg", "author": "AHS Crave", "viewCount": "13840", "datePublished": "2021-08-26", "likes": "243", "dislikes": "3", "comment": ["She looks just like her mother.\n\nR.I.P, Carrie Fisher.", "We can talk about Doris taking hours to choose which gray to wear, I love her", "I love her already.", "I\u2019m pretty sure that the daughter is played by Vickie from It Chapter 2(the little girl with the birthmark).", "Lol Lark managed to make dental caps in 1 day?\n\nNot 6 months? She's one hell of a tooth jocky"], "authorLink": "https://www.youtube.com/channel/UC0xpCvB57MXDhrVOryp1z3g", "description": "\"Pale\", the second episode of American Horror Story: Double Feature (Part 1 - Red Tide) - written by Brad Falchuk & Ryan Murphy, directed by Loni Peristere - stars Sarah Paulson as Tuberculosis Karen, Evan Peters as Austin Sommers, Lily Rabe as Doris Gardener, Finn Wittrock as Harry Gardener, Ryan Kiera Armstrong as Alma Gardener, Frances Conroy as Belle Noir, Billie Lourd as Lark, Leslie Grossman as Ursula, Adina Porter as Chief Burelson, Angelica Ross as The Chemist, Macaulay Culkin as Mickey, Denis O'Hare as Holden, and Robin Weigert as Martha. All rights belong to FX Networks and Ryan Murphy Television."}