{"title": "Suicide squad - the enchantress escapes from waller and builds her weapon with her brother", "url": "https://www.youtube.com/watch?v=Cdnyo0KT-8M", "image": "https://i.ytimg.com/vi/Cdnyo0KT-8M/hqdefault.jpg", "author": "ONCEUPON a HORRORSTORY", "viewCount": "355970", "datePublished": "2016-10-16", "likes": "1,006", "dislikes": "91", "comment": ["I'd like to see Loki and Enchantress face off to see who has the silliest helmet.", "\"I thought this was contained\" I found that hilarious", "OMG her portrayal of the enchantress was so on point.\n\nAnd by that I mean on point of a knife that I just wanted to put in her chest and say NO!!!", "I looked up \"suicide squad enchantress dance,\" and this came up.", "she's so beautiful in goddess mode, she reminds me of circe"], "authorLink": "https://www.youtube.com/channel/UCGIQHvkZPzrna7UHtmlgoXw", "description": "Suicide squad - the enchantress escapes from waller and builds her weapon with her brother"}