{"title": "Person of Interest - John Reese meets up with his old friends (Season 1 Episode 1)", "url": "https://www.youtube.com/watch?v=G0kxDLP26QA", "image": "https://i.ytimg.com/vi/G0kxDLP26QA/maxresdefault.jpg", "author": "Machine of Interest", "viewCount": "239", "datePublished": "2018-06-17", "likes": "4", "dislikes": "0", "comment": [], "authorLink": "https://www.youtube.com/channel/UCZlhBRWDNf1gXLE-JatLP6w", "description": "Machine of Interest - A YouTube channel created for the television series \"Person of Interest\". This YouTube channel displays small clips from the series.\n------------------------------------------------------------------------------------------\nTwitter - "}