{"title": "Half a Million Dollars (Person of Interest)(1 x 14)", "url": "https://www.youtube.com/watch?v=Jnp5YN8NpZQ", "image": "https://i.ytimg.com/vi/Jnp5YN8NpZQ/maxresdefault.jpg", "author": "Person of Interest Highlights", "viewCount": "1423", "datePublished": "2017-04-08", "likes": "17", "dislikes": "0", "comment": ["@Person of Interest Highlights.....THX for this awesome video. I'm getting goosebumbs when I see John Reeses eyes. They are so beautiful and yet can be so frightening when he wants them to be. Jim Caviezel has the ability to use his impressive eyes in such a powerful way as I have never seen before. I love it! <3 <3<<3"], "authorLink": "https://www.youtube.com/channel/UCN_n9HC4_nauZgeANSpXP_Q", "description": "John interrogates a grunt on the location of a murder weapon.\n\nI do not own Person of Interest, All rights go to its respective creators and distributors."}