{"title": "Lady Gaga starring in American Horror Story Hotel", "url": "https://www.youtube.com/watch?v=KL58ZEKnVf8", "image": "https://i.ytimg.com/vi/KL58ZEKnVf8/maxresdefault.jpg", "author": "American Horror Story Brasil", "viewCount": "3349", "datePublished": "2015-02-28", "likes": "135", "dislikes": "1", "comment": ["MEU DEUS", "OMG LADY GAGA \ud83d\ude0d\ud83d\ude0d", "Uhuh"], "authorLink": "https://www.youtube.com/channel/UC3csl_yNKV--YULIQOL13rA", "description": "We don't own the rights to this song and the video. All the rights belong to the owner of the song and FX. We're not profiting by publishing."}