{"title": "Royal Pains - Opening Intro", "url": "https://www.youtube.com/watch?v=KNoRCVrRlGg", "image": "https://i.ytimg.com/vi/KNoRCVrRlGg/maxresdefault.jpg", "author": "GotPilot", "viewCount": "8064", "datePublished": "2015-10-09", "likes": "49", "dislikes": "3", "comment": ["South Park Scrubs Comics Un. HOUSE OF PAYNE ONE ON ONE HALF & HALF EYE FOR AN EYE LITTLE HOUSE ON THE PRAIRIE CHEATERS THE INSIDER"], "authorLink": "https://www.youtube.com/channel/UCNFORB3o9Bg3d6FiAfdUL1A", "description": ""}