{"title": "The Day Grunge Died: A Kurt Cobain Live Stream Tribute 2018", "url": "https://www.youtube.com/watch?v=KyA42gNT5w0", "image": "https://i.ytimg.com/vi/KyA42gNT5w0/hqdefault.jpg", "author": "MaryGirl Moody", "viewCount": "378", "datePublished": "2018-04-05", "likes": "22", "dislikes": "0", "comment": ["Thank you for this. He's one of my favorite artists", "Sorry to miss y\u2019all, my girls are in town for Easter. Courtney totally did it, no way he could have done that to himself anyway.\n...hey Mary are you still working on your very first 5 Patreon patrons request videos? Mine was supposed be a look at all the connections, parallels and symbolism throughout the American Horror Story universe.", "If Courtney had anything to do with Kurt\u2019s passing it won\u2019t be said till she passes herself", "CONTEST ONLY APPLIED TO THE LIVE STREAM AND IS OVER!", "Grunge is my religion"], "authorLink": "https://www.youtube.com/channel/UCc5rwO1EcnOo6ydOmGItlGQ", "description": "For me and thousands of other fans, grunge music died the day Kurt Cobain left this mortal coil. Everyone is welcome to chat live about Kurt, Nirvana, and any topic that comes to their mind as we approach 24 years since the day grunge died.\n\nHost is MaryGirl Moody.\n\nASSHOLES ARE WELCOMED, DICKHOLES ARE BANNED.\n\nGo here for the official Nirvana website: "}