{"title": "Person of Interest: Reese & Finch VS Extortionist Assasin", "url": "https://www.youtube.com/watch?v=lAAHPdQ5E9w", "image": "https://i.ytimg.com/vi/lAAHPdQ5E9w/maxresdefault.jpg", "author": "POI Fights", "viewCount": "21596", "datePublished": "2015-02-19", "likes": "140", "dislikes": "3", "comment": ["Can you get the scene of Root saving Finch from Claire", "Nice. Thanks for this.", "In hindsight, isn't this scene a little cheese in the sense that the bad guy needs to talk and explain his motives to Harold and Emma just give Mr. Reese enough time to get there and save them? I mean, why didn't he just kill Finch instead of talking and explaining why he's about to kill him?", "did it look like john took that chair to the back so harold wouldnt? or is that just my imagination <3 ship them so much"], "authorLink": "https://www.youtube.com/channel/UCjCe8KE9b9WNIw661h9gQnw", "description": "Fight Scene from S04 X E14: Guilty"}