{"title": "\"Somebody Killed My Best Friend!\" | Good Omens | Prime Video", "url": "https://www.youtube.com/watch?v=Lcr_jlhO948", "image": "https://i.ytimg.com/vi/Lcr_jlhO948/maxresdefault.jpg", "author": "Amazon Prime Video UK", "viewCount": "101522", "datePublished": "2021-02-15", "likes": "1,866", "dislikes": "45", "comment": ["It's okay Crowley, he's only been discorporated...", "Can we all appreciate that Crowley said \u201cfor heaven\u2019s sake\u201d for Aziraphale?", "I was totally not expecting Aziraphale to curse but it was genuinely surprising and hilarious", "Just realized the reference from Crowley snapping his fingers to open the door of the bookshop, since it's the same way the TARDIS doors open.", "1:00 \"Seducing women to do your evil will!\"\n\"I think perhaps you have the wrong shop.\"\n\nHow has no one mentioned this part...?"], "authorLink": "https://www.youtube.com/channel/UCwSIJCMWZC5GDM59wj7pMsg", "description": "After Aziraphale is 'exorcised' by Shadwell, Crowley is left missing his best friend in the remains of his burning bookshop.\n\u00bb SUBSCRIBE: http://www.youtube.com/channel/UCwSIJ..."}