{"title": "Person Of Interest Soundtrack: 4x22 The Correction", "url": "https://www.youtube.com/watch?v=NRZuUESwWWs", "image": "https://i.ytimg.com/vi/NRZuUESwWWs/maxresdefault.jpg", "author": "FringeMusic107", "viewCount": "13037", "datePublished": "2015-05-06", "likes": "92", "dislikes": "0", "comment": ["The best finale of all series. Honestly I didn't think Elias would die.", "Themes used:\n0:00 Control's theme\n0:17 Samaritan's theme\n0:29 Reese's theme", "the season finale was epic.. thanks for the soundtrack", "the part mix machine's ,Samaritan's and Finch's theme is awesome", "Truly, spectacular, Djawadi really needs to release his work more often. Thanks for the video.\nThough I didn't hear one part that I REALLY wanted to hear (or I might be deaf and don't recognize it).\n(Spoilers)"], "authorLink": "https://www.youtube.com/channel/UCGU3fjBOY4CYJPgP7W-bguA", "description": "Whew! How 'bout that season finale? Soundtrack from Person Of Interest episode 4x22 \"YHWH\". Composed by Ramin Djawadi."}