{"title": "D\u00e1 pra confiar em algu\u00e9m? Review AHS: 1984 Ep. 3", "url": "https://www.youtube.com/watch?v=nXY6ljCD42g", "image": "https://i.ytimg.com/vi/nXY6ljCD42g/maxresdefault.jpg", "author": "American Horror Story Brasil", "viewCount": "4468", "datePublished": "2019-10-08", "likes": "767", "dislikes": "15", "comment": ["Pra mim foi o melhor epis\u00f3dio da temporada", "como assim? achei o melhor epis\u00f3dio e outra... as armadilhas vc n\u00e3o achou estranho? parece um campo de prova", "eu fico assustada com teu senso cr\u00edtico, tudo pra mim \u00e9 bom kkkkk monstro!", "Pq ningu\u00e9m t\u00e1 ligando pro fato de que o mr jingles disse pra Dona que ele n\u00e3o se lembra de ter matado os adolescentes no massacre de 1970?", "Eu achei estranha a frase do Ray: \"Que veria o acampamento em outra vida\"."], "authorLink": "https://www.youtube.com/channel/UC3csl_yNKV--YULIQOL13rA", "description": "N\u00c3O ESQUE\u00c7AM DE NOS SEGUIR NAS NOSSAS REDES SOCIAIS:\n\nP\u00e1gina do Facebook: https://www.facebook.com/AmericanHorr..."}