{"title": "American Horror Story: Double Feature S10 E01 & E02 Trailer | Rotten Tomatoes TV", "url": "https://www.youtube.com/watch?v=rgAoKo-Q8Jw", "image": "https://i.ytimg.com/vi/rgAoKo-Q8Jw/hqdefault.jpg", "author": "Rotten Tomatoes TV", "viewCount": "5844", "datePublished": "2021-08-26", "likes": "91", "dislikes": "5", "comment": ["Can't wait to watch!", "now listen guys ... 0:30 could be doris after she took the pills", "Song?"], "authorLink": "https://www.youtube.com/channel/UCz1GPotHecuLngiLuY739QQ", "description": "Check out the new American Horror Story: Double Feature S10 E01 & E02 Trailer Neal McDonough! Let us know what you think in the comments below.\n\u25ba Learn more about this show on Rotten Tomatoes: https://www.rottentomatoes.com/tv/ame..."}