{"title": "John vs Anthony (Person of Interest)(1 x 19)", "url": "https://www.youtube.com/watch?v=RlDk1D24mys", "image": "https://i.ytimg.com/vi/RlDk1D24mys/hqdefault.jpg", "author": "Person of Interest Highlights", "viewCount": "1030", "datePublished": "2017-04-19", "likes": "15", "dislikes": "0", "comment": [], "authorLink": "https://www.youtube.com/channel/UCN_n9HC4_nauZgeANSpXP_Q", "description": "John assaults Elias's compound and saves Carter's son.\n\nI do not own Person of Interest, all rights go to its producers and distributors."}