{"title": "Person of Interest: Crossfire", "url": "https://www.youtube.com/watch?v=ryMDQdiS954", "image": "https://i.ytimg.com/vi/ryMDQdiS954/maxresdefault.jpg", "author": "S. O.", "viewCount": "5431", "datePublished": "2016-01-08", "likes": "155", "dislikes": "1", "comment": [], "authorLink": "https://www.youtube.com/channel/UCc346thcxcLzo1A80xGmIWg", "description": "To try and cope with the unknown return of POI, I cure myself by doing these. I hope you like it, I really enjoyed making this one.\n\nFandom: Person of Interest\nSong: Stephen - Crossfire\n_______________________________________\n\nNo Copyright Infringement Intended"}