{"title": "AHS Apocalypse Episode 10 Review SPOILERS!!", "url": "https://www.youtube.com/watch?v=t6QDAPimVsA", "image": "https://i.ytimg.com/vi/t6QDAPimVsA/hqdefault.jpg", "author": "MaryGirl Moody", "viewCount": "33780", "datePublished": "2018-11-14", "likes": "945", "dislikes": "50", "comment": ["They seriously only brought Marie Laveaux back long enough to throw her braids over her shoulder ONE time!\ud83d\ude2d", "My favourite line was myrtle to madison \"you grab the gasoline i grab the wood\" the delivery was pure comedy gold", "Timothy and Emily\u2019s child being the Antichrist was a foreshadowing of the 1st episode when Timothy got out of the shower and saw 666 written on the mirror and a voice said beware", "\"We modeled her personality after Madison\" DEAD. <3", "I guess when Venable said \"no unauthorized copulation\" there was a good reason; those 2 were destined to give birth to the real devil baby!"], "authorLink": "https://www.youtube.com/channel/UCc5rwO1EcnOo6ydOmGItlGQ", "description": "\u25ba \u25ba SUBSCRIBE https://www.youtube.com/channel/UCc5r...\n\nFX Plus: https://fxplus.fxnetworks.com"}