{"title": "American Horror Story Freak Show : Back to Back (Official Teaser 13)", "url": "https://www.youtube.com/watch?v=To2imIv0JNs", "image": "https://i.ytimg.com/vi/To2imIv0JNs/maxresdefault.jpg", "author": "AHS Greece", "viewCount": "1525", "datePublished": "2014-09-23", "likes": "17", "dislikes": "0", "comment": ["this is my favorite teaser!"], "authorLink": "https://www.youtube.com/channel/UCC27Xgd5Y_r8lNt6eFlU1yQ", "description": "American Horror Story Freak Show : Back to Back (Official Teaser 13)"}