{"title": "American horror story asylum -  welcome to Briarcliff", "url": "https://www.youtube.com/watch?v=TXHliC4d1iA", "image": "https://i.ytimg.com/vi/TXHliC4d1iA/hqdefault.jpg", "author": "ONCEUPON a HORRORSTORY", "viewCount": "79642", "datePublished": "2016-09-10", "likes": "841", "dislikes": "10", "comment": ["Asylum is by far the best season, in my personal opinion.", "It\u2019s so sad to think that Pepper was always introduced as a baby killer. Imagine being unable to defend yourself and wanting to make a friend only to be cast as a horrible person.", "PEPPER WAS FRAMED!", "I love this introduction of Lana. Her high heal crushing the cigarette, the fixing of her hair, the Carrie theme. Awesome", "Sister Jude was def my favourite of Jessica Langes AHS roles."], "authorLink": "https://www.youtube.com/channel/UCGIQHvkZPzrna7UHtmlgoXw", "description": "American horror story asylum - Lana winters visits the asylum \n2x1 welcome to Briarcliff"}