{"title": "Beyond the Horror: Murder House Episode 11", "url": "https://www.youtube.com/watch?v=v4o7bV2CgC0", "image": "https://i.ytimg.com/vi/v4o7bV2CgC0/maxresdefault.jpg", "author": "MaryGirl Moody", "viewCount": "449", "datePublished": "2017-03-22", "likes": "23", "dislikes": "2", "comment": [], "authorLink": "https://www.youtube.com/channel/UCc5rwO1EcnOo6ydOmGItlGQ", "description": "VIDEO CONTAINS SPOILERS FOR SEASON ONE, EPISODE 11 OF AMERICAN HORROR STORY!!!\n\nBeyond the Horror: Murder House, is an unofficial American Horror Story Live After Show. Hosted by MaryGirl Moody with Tami Sifford. We discuss and review each episode of American Horror Story Murder House. Join the Freaks of AHS on Facebook (link below), and Beyond the Horror. "}