{"title": "Person of Interest - 2x13 - Dead Reckoning - Bande-annonce courte VOSTFR", "url": "https://www.youtube.com/watch?v=Vz8_TpIEhME", "image": "https://i.ytimg.com/vi/Vz8_TpIEhME/maxresdefault.jpg", "author": "PersonOfInterestFR", "viewCount": "447", "datePublished": "2013-08-02", "likes": "0", "dislikes": "0", "comment": [], "authorLink": "https://www.youtube.com/channel/UC7MU-uVNRORGnn9TbsOgE2w", "description": "Apr\u00e8s avoir embouti la voiture de Donnelley et tu\u00e9 ce dernier, Kara enl\u00e8ve Reese comme elle l'a fait avec Snow. Apr\u00e8s leur avoir ceintur\u00e9 une bombe, elle les force \u00e0 se rendre dans un \u00e9tablissement ultra-s\u00e9curis\u00e9, tandis que Finch, Carter et Fusco tentent de les retrouver.\n\nCette vid\u00e9o est la propri\u00e9t\u00e9 de Warner Bros Entertainment, Bad Robot, CBS et Kilter Films. VO/Traduction/Synchro : Paidon.\n\nRestez inform\u00e9s, rejoignez-nous : "}