{"title": "Person of Interest: Reese VS Marshals", "url": "https://www.youtube.com/watch?v=WVrNO3YsWRE", "image": "https://i.ytimg.com/vi/WVrNO3YsWRE/hqdefault.jpg", "author": "POI Fights", "viewCount": "31352", "datePublished": "2014-03-15", "likes": "227", "dislikes": "5", "comment": ["Ironic how Quinn is the one to give probably the best tribute to Reese's abilities in the whole show.", "I could watch POI all over again.", "What\u2019s name of the background music?", "Anyone  know the song name"], "authorLink": "https://www.youtube.com/channel/UCjCe8KE9b9WNIw661h9gQnw", "description": "Fight Scene from S03 X 10: The Devil's Share"}