{"title": "\u25ba ALL TEASERS American Horror Story 4: Freak Show // Promos from #1 to #12", "url": "https://www.youtube.com/watch?v=YDU4Ca3HEds", "image": "https://i.ytimg.com/vi/YDU4Ca3HEds/hqdefault.jpg", "author": "American Horror Story 10", "viewCount": "8786", "datePublished": "2014-09-19", "likes": "81", "dislikes": "3", "comment": ["Excelente recopilaci\u00f3n,,  que contento\nestoy de mi serie favorita", "They make the teasers look scarier than the seasons", "I think 1:57 is a reference to the Slender Man.", "That's so gross I'm not going to eat a sucker"], "authorLink": "https://www.youtube.com/channel/UClGiNHyDZPm4jEOo9UyP5Zw", "description": "OFFICIAL PROMOS of Ryan Murphy's TvSeries. With Jessica Lange, Sarah Paulson, Jamie Brewer, Angela Bassett, Kathy Bates, Michael Chiklis, Evan Peters, Frances Conroy, Emma Roberts, and Denis O\u2019Hare.\nCOMPILATION."}