{"title": "American Horror Story: Apocalypse - theme music (HQ)", "url": "https://www.youtube.com/watch?v=zWdXBlmy5RE", "image": "https://i.ytimg.com/vi/zWdXBlmy5RE/hqdefault.jpg", "author": "American Horror Story: Croatia", "viewCount": "4776", "datePublished": "2018-12-17", "likes": "129", "dislikes": "0", "comment": ["This is almost a better opening than the original", "Nuevas series de terror Adam Jackson David condoleo y Finn wolfhard y Jack Dylan grazer y Wyatt oleff y jaremy Ray Taylor y Sophia Lilis y jaeden Martell lieberher y Wyatt oleff y Owen vaccaro y Jacob tremblay y Jacob lundqvist y Thomas barusca y bryce gheisar y Noah schnapp y  emma Roberts y Ariana grande y Issac Seth Johnson y adexe y nau y Will buie JR y Asher angel y china Anne mcclain y Freddie higmore y Bill Skarsgard y mille bobby Brown y Issac Presley y Dakota Lotus y Issac Ryan Brown y gaten marattazzo  y Jane lynch y lady Gaga y Rihanna y roman christou y Gabriel Bateman y lea Michele y Peyton wich y  Sarah Jeffery y J\u00e9ssica Lange y J\u00e9ssica L\u00f3pez y keeke Palmer y  Owen vaccaro y sunny sulijc y Paxton booth y Paxton singleton y Justin Paul Kelly y Daniel huttlstone y asa Buttifiled y Frank dorsin y Daniel damaggio y ky Baldwin Dove Cameron y Lincoln melcher  american horror story  la amenaza pennywise final temporada Estron  16 de octubre temporada  2020"], "authorLink": "https://www.youtube.com/channel/UCbqN5wuVJi2x8RL3OFNjsUg", "description": "American Horror Story: Apocalypse - theme music (HQ)\nAmeri\u010dka horor pri\u010da: Apokalipsa"}