{"name": "ABC 7 Chicago", "follower": "15.6K", "link": "https://www.youtube.com/channel/UC_vFLohxs5PkAxlk7Y6jEtw", "image": "https://yt3.ggpht.com/ytc/AKedOLQIuxsosgerTjb5ay4c5r-LuJC05SzHMAAdO_ADjJk=s176-c-k-c0x00ffffff-no-rj", "profile": "Chicago's source for news video online.  Covering news, consumer stories, investigations, weather, entertainment, health, lifestyle, sports and more.\n\nHere, we explore fresh stories inspired by the Chicago area that resonate with our global community. Keep your eyes on this channel for more details about your neighborhood and your neighbors! Subscribe today!"}